AUTHORS
LICENSE.txt
MANIFEST.in
README.md
setup.py
snaptastic/__init__.py
snaptastic/cleaner.py
snaptastic/cli.py
snaptastic/default_settings.py
snaptastic/ebs_volume.py
snaptastic/examples.py
snaptastic/exceptions.py
snaptastic/freeze.py
snaptastic/metaclass.py
snaptastic/settings.py
snaptastic/snapshotter.py
snaptastic/tests.py
snaptastic.egg-info/PKG-INFO
snaptastic.egg-info/SOURCES.txt
snaptastic.egg-info/dependency_links.txt
snaptastic.egg-info/entry_points.txt
snaptastic.egg-info/not-zip-safe
snaptastic.egg-info/requires.txt
snaptastic.egg-info/top_level.txt
snaptastic/utils/__init__.py
snaptastic/utils/dictconfig.py
snaptastic/utils/log.py
snaptastic/utils/sub.py