Metadata-Version: 1.0
Name: snaptastic
Version: 0.2.6
Summary: Snaptastic is a python tool to enable easy snapshotting
